mlinsights-0.5.3.dist-info/RECORD
mlinsights-0.5.3.dist-info/WHEEL
mlinsights-0.5.3.dist-info/top_level.txt
mlinsights-0.5.3.dist-info/METADATA
mlinsights-0.5.3.dist-info/licenses/LICENSE.txt
mlinsights/__init__.py
mlinsights/ext_test_case.py
mlinsights/_config.py
mlinsights/search_rank/search_engine_vectors.py
mlinsights/search_rank/search_engine_predictions.py
mlinsights/search_rank/__init__.py
mlinsights/search_rank/search_engine_predictions_images.py
mlinsights/metrics/__init__.py
mlinsights/metrics/correlations.py
mlinsights/metrics/scoring_metrics.py
mlinsights/timeseries/metrics.py
mlinsights/timeseries/patterns.py
mlinsights/timeseries/plotting.py
mlinsights/timeseries/datasets.py
mlinsights/timeseries/__init__.py
mlinsights/timeseries/utils.py
mlinsights/timeseries/preprocessing.py
mlinsights/timeseries/ar.py
mlinsights/timeseries/dummies.py
mlinsights/timeseries/agg.py
mlinsights/timeseries/base.py
mlinsights/mlbatch/pipeline_cache.py
mlinsights/mlbatch/__init__.py
mlinsights/mlbatch/cache_model.py
mlinsights/mlmodel/sklearn_transform_inv.py
mlinsights/mlmodel/_piecewise_tree_regression_common.cpp
mlinsights/mlmodel/piecewise_tree_regression_criterion_linear.cpython-313-darwin.so
mlinsights/mlmodel/anmf_predictor.py
mlinsights/mlmodel/categories_to_integers.py
mlinsights/mlmodel/_kmeans_022.py
mlinsights/mlmodel/_piecewise_tree_regression_common.pxd
mlinsights/mlmodel/direct_blas_lapack.cpp
mlinsights/mlmodel/interval_regressor.py
mlinsights/mlmodel/piecewise_tree_regression_criterion_fast.cpp
mlinsights/mlmodel/piecewise_tree_regression.py
mlinsights/mlmodel/piecewise_tree_regression_criterion_fast.cpython-313-darwin.so
mlinsights/mlmodel/kmeans_constraint.py
mlinsights/mlmodel/target_predictors.py
mlinsights/mlmodel/piecewise_tree_regression_criterion_linear.pyx
mlinsights/mlmodel/quantile_mlpregressor.py
mlinsights/mlmodel/piecewise_tree_regression_criterion.pyx
mlinsights/mlmodel/direct_blas_lapack.cpython-313-darwin.so
mlinsights/mlmodel/piecewise_tree_regression_criterion.cpython-313-darwin.so
mlinsights/mlmodel/ml_featurizer.py
mlinsights/mlmodel/__init__.py
